{"box_data": [{"position": {"minX": 271.5, "minY": 215.0, "maxX": 446.0, "maxY": 362.5}, "class_id": 1, "box_caption": "other objects 0.943", "scores": {"class_score": 0.943359375}, "domain": "pixel"}, {"position": {"minX": 580.5, "minY": 230.0, "maxX": 655.5, "maxY": 333.0}, "class_id": 1, "box_caption": "other objects 0.933", "scores": {"class_score": 0.9326171875}, "domain": "pixel"}, {"position": {"minX": 431.0, "minY": 177.625, "maxX": 528.5, "maxY": 424.0}, "class_id": 1, "box_caption": "other objects 0.839", "scores": {"class_score": 0.8388671875}, "domain": "pixel"}, {"position": {"minX": 165.25, "minY": 230.5, "maxX": 182.5, "maxY": 283.5}, "class_id": 0, "box_caption": "small objects 0.611", "scores": {"class_score": 0.61083984375}, "domain": "pixel"}, {"position": {"minX": 426.75, "minY": 228.125, "maxX": 452.75, "maxY": 260.0}, "class_id": 0, "box_caption": "small objects 0.211", "scores": {"class_score": 0.2105712890625}, "domain": "pixel"}, {"position": {"minX": 153.0, "minY": 233.625, "maxX": 167.25, "maxY": 281.25}, "class_id": 0, "box_caption": "small objects 0.205", "scores": {"class_score": 0.204833984375}, "domain": "pixel"}, {"position": {"minX": 426.5, "minY": 227.875, "maxX": 453.5, "maxY": 287.5}, "class_id": 1, "box_caption": "other objects 0.074", "scores": {"class_score": 0.07373046875}, "domain": "pixel"}, {"position": {"minX": 426.5, "minY": 227.25, "maxX": 453.0, "maxY": 261.75}, "class_id": 1, "box_caption": "other objects 0.045", "scores": {"class_score": 0.045440673828125}, "domain": "pixel"}, {"position": {"minX": 165.375, "minY": 229.625, "maxX": 182.375, "maxY": 284.0}, "class_id": 1, "box_caption": "other objects 0.035", "scores": {"class_score": 0.035400390625}, "domain": "pixel"}, {"position": {"minX": 421.25, "minY": 294.0, "maxX": 549.0, "maxY": 432.0}, "class_id": 1, "box_caption": "other objects 0.033", "scores": {"class_score": 0.033447265625}, "domain": "pixel"}, {"position": {"minX": 422.25, "minY": 232.75, "maxX": 455.75, "maxY": 315.75}, "class_id": 1, "box_caption": "other objects 0.028", "scores": {"class_score": 0.02825927734375}, "domain": "pixel"}, {"position": {"minX": 424.25, "minY": 203.125, "maxX": 488.75, "maxY": 402.0}, "class_id": 1, "box_caption": "other objects 0.022", "scores": {"class_score": 0.0221710205078125}, "domain": "pixel"}, {"position": {"minX": 427.0, "minY": 225.375, "maxX": 450.0, "maxY": 249.875}, "class_id": 0, "box_caption": "small objects 0.016", "scores": {"class_score": 0.0157623291015625}, "domain": "pixel"}, {"position": {"minX": 426.5, "minY": 227.875, "maxX": 453.5, "maxY": 287.5}, "class_id": 0, "box_caption": "small objects 0.015", "scores": {"class_score": 0.01517486572265625}, "domain": "pixel"}, {"position": {"minX": 152.875, "minY": 232.75, "maxX": 168.125, "maxY": 284.75}, "class_id": 1, "box_caption": "other objects 0.012", "scores": {"class_score": 0.01219940185546875}, "domain": "pixel"}, {"position": {"minX": 469.5, "minY": 306.75, "maxX": 542.5, "maxY": 428.75}, "class_id": 1, "box_caption": "other objects 0.012", "scores": {"class_score": 0.0121307373046875}, "domain": "pixel"}, {"position": {"minX": 461.5, "minY": 187.75, "maxX": 541.0, "maxY": 414.25}, "class_id": 1, "box_caption": "other objects 0.008", "scores": {"class_score": 0.008392333984375}, "domain": "pixel"}, {"position": {"minX": 422.25, "minY": 229.25, "maxX": 463.25, "maxY": 346.25}, "class_id": 1, "box_caption": "other objects 0.005", "scores": {"class_score": 0.0054168701171875}, "domain": "pixel"}, {"position": {"minX": 414.75, "minY": 221.25, "maxX": 461.25, "maxY": 304.25}, "class_id": 1, "box_caption": "other objects 0.005", "scores": {"class_score": 0.005260467529296875}, "domain": "pixel"}, {"position": {"minX": 402.25, "minY": 201.0, "maxX": 510.75, "maxY": 412.0}, "class_id": 1, "box_caption": "other objects 0.005", "scores": {"class_score": 0.004764556884765625}, "domain": "pixel"}, {"position": {"minX": 426.0, "minY": 202.375, "maxX": 475.5, "maxY": 358.0}, "class_id": 1, "box_caption": "other objects 0.005", "scores": {"class_score": 0.004673004150390625}, "domain": "pixel"}, {"position": {"minX": 167.75, "minY": 230.875, "maxX": 183.0, "maxY": 264.5}, "class_id": 0, "box_caption": "small objects 0.004", "scores": {"class_score": 0.00379180908203125}, "domain": "pixel"}, {"position": {"minX": 434.25, "minY": 222.25, "maxX": 457.75, "maxY": 295.25}, "class_id": 1, "box_caption": "other objects 0.003", "scores": {"class_score": 0.0029811859130859375}, "domain": "pixel"}, {"position": {"minX": 426.0, "minY": 175.0, "maxX": 531.0, "maxY": 427.0}, "class_id": 0, "box_caption": "small objects 0.002", "scores": {"class_score": 0.0022830963134765625}, "domain": "pixel"}, {"position": {"minX": 269.0, "minY": 214.0, "maxX": 441.5, "maxY": 365.0}, "class_id": 0, "box_caption": "small objects 0.002", "scores": {"class_score": 0.002223968505859375}, "domain": "pixel"}, {"position": {"minX": 481.5, "minY": 224.5, "maxX": 550.5, "maxY": 443.0}, "class_id": 1, "box_caption": "other objects 0.002", "scores": {"class_score": 0.0019006729125976562}, "domain": "pixel"}, {"position": {"minX": 418.25, "minY": 233.625, "maxX": 474.75, "maxY": 384.5}, "class_id": 1, "box_caption": "other objects 0.002", "scores": {"class_score": 0.0016107559204101562}, "domain": "pixel"}, {"position": {"minX": 424.5, "minY": 222.25, "maxX": 456.0, "maxY": 254.5}, "class_id": 0, "box_caption": "small objects 0.001", "scores": {"class_score": 0.0014581680297851562}, "domain": "pixel"}, {"position": {"minX": 154.375, "minY": 231.375, "maxX": 167.625, "maxY": 265.25}, "class_id": 0, "box_caption": "small objects 0.001", "scores": {"class_score": 0.0013942718505859375}, "domain": "pixel"}, {"position": {"minX": 466.5, "minY": 315.75, "maxX": 522.5, "maxY": 418.25}, "class_id": 1, "box_caption": "other objects 0.001", "scores": {"class_score": 0.0013761520385742188}, "domain": "pixel"}, {"position": {"minX": 423.5, "minY": 229.75, "maxX": 446.5, "maxY": 255.5}, "class_id": 0, "box_caption": "small objects 0.001", "scores": {"class_score": 0.0013551712036132812}, "domain": "pixel"}, {"position": {"minX": 419.25, "minY": 246.5, "maxX": 502.75, "maxY": 431.5}, "class_id": 1, "box_caption": "other objects 0.001", "scores": {"class_score": 0.00131988525390625}, "domain": "pixel"}, {"position": {"minX": 424.75, "minY": 321.75, "maxX": 512.0, "maxY": 409.75}, "class_id": 1, "box_caption": "other objects 0.001", "scores": {"class_score": 0.0012865066528320312}, "domain": "pixel"}, {"position": {"minX": 418.25, "minY": 231.375, "maxX": 448.25, "maxY": 303.0}, "class_id": 1, "box_caption": "other objects 0.001", "scores": {"class_score": 0.0011987686157226562}, "domain": "pixel"}, {"position": {"minX": 426.25, "minY": 211.25, "maxX": 482.75, "maxY": 290.0}, "class_id": 1, "box_caption": "other objects 0.001", "scores": {"class_score": 0.00119781494140625}, "domain": "pixel"}, {"position": {"minX": 579.5, "minY": 229.875, "maxX": 655.5, "maxY": 334.25}, "class_id": 0, "box_caption": "small objects 0.001", "scores": {"class_score": 0.001178741455078125}, "domain": "pixel"}, {"position": {"minX": 435.25, "minY": 227.125, "maxX": 455.25, "maxY": 261.5}, "class_id": 0, "box_caption": "small objects 0.001", "scores": {"class_score": 0.0010042190551757812}, "domain": "pixel"}], "class_labels": {"0": "small objects", "1": "other objects"}}