{"box_data": [{"position": {"minX": 155.375, "minY": 261.5, "maxX": 217.625, "maxY": 382.5}, "class_id": 1, "box_caption": "Leconte 0.662", "scores": {"class_score": 0.66162109375}, "domain": "pixel"}, {"position": {"minX": 244.25, "minY": 556.0, "maxX": 321.75, "maxY": 619.0}, "class_id": 1, "box_caption": "Leconte 0.477", "scores": {"class_score": 0.47705078125}, "domain": "pixel"}, {"position": {"minX": 155.375, "minY": 261.5, "maxX": 217.625, "maxY": 382.5}, "class_id": 0, "box_caption": "Boerner 0.421", "scores": {"class_score": 0.4208984375}, "domain": "pixel"}, {"position": {"minX": 295.0, "minY": 298.0, "maxX": 313.0, "maxY": 327.5}, "class_id": 5, "box_caption": "coleoptera 0.303", "scores": {"class_score": 0.302978515625}, "domain": "pixel"}, {"position": {"minX": 392.25, "minY": 341.75, "maxX": 434.25, "maxY": 411.75}, "class_id": 1, "box_caption": "Leconte 0.293", "scores": {"class_score": 0.292724609375}, "domain": "pixel"}, {"position": {"minX": 159.125, "minY": 280.5, "maxX": 213.875, "maxY": 362.0}, "class_id": 1, "box_caption": "Leconte 0.264", "scores": {"class_score": 0.263671875}, "domain": "pixel"}, {"position": {"minX": 393.75, "minY": 339.75, "maxX": 431.25, "maxY": 416.25}, "class_id": 0, "box_caption": "Boerner 0.238", "scores": {"class_score": 0.2376708984375}, "domain": "pixel"}, {"position": {"minX": 240.25, "minY": 555.0, "maxX": 327.25, "maxY": 617.0}, "class_id": 0, "box_caption": "Boerner 0.216", "scores": {"class_score": 0.2156982421875}, "domain": "pixel"}, {"position": {"minX": 229.25, "minY": 436.25, "maxX": 279.25, "maxY": 473.25}, "class_id": 1, "box_caption": "Leconte 0.202", "scores": {"class_score": 0.202392578125}, "domain": "pixel"}, {"position": {"minX": 321.75, "minY": 441.25, "maxX": 372.75, "maxY": 472.25}, "class_id": 1, "box_caption": "Leconte 0.198", "scores": {"class_score": 0.1982421875}, "domain": "pixel"}, {"position": {"minX": 292.5, "minY": 299.75, "maxX": 313.5, "maxY": 327.25}, "class_id": 4, "box_caption": "armandi 0.196", "scores": {"class_score": 0.19580078125}, "domain": "pixel"}, {"position": {"minX": 238.25, "minY": 361.5, "maxX": 267.5, "maxY": 403.0}, "class_id": 4, "box_caption": "armandi 0.183", "scores": {"class_score": 0.1834716796875}, "domain": "pixel"}, {"position": {"minX": 224.375, "minY": 440.0, "maxX": 282.0, "maxY": 470.5}, "class_id": 0, "box_caption": "Boerner 0.179", "scores": {"class_score": 0.17919921875}, "domain": "pixel"}, {"position": {"minX": 321.75, "minY": 441.25, "maxX": 372.75, "maxY": 472.25}, "class_id": 4, "box_caption": "armandi 0.163", "scores": {"class_score": 0.162841796875}, "domain": "pixel"}, {"position": {"minX": 239.5, "minY": 359.75, "maxX": 266.25, "maxY": 402.25}, "class_id": 5, "box_caption": "coleoptera 0.157", "scores": {"class_score": 0.157470703125}, "domain": "pixel"}, {"position": {"minX": 318.25, "minY": 443.75, "maxX": 375.75, "maxY": 470.75}, "class_id": 0, "box_caption": "Boerner 0.157", "scores": {"class_score": 0.1573486328125}, "domain": "pixel"}, {"position": {"minX": 395.0, "minY": 340.0, "maxX": 431.0, "maxY": 414.0}, "class_id": 4, "box_caption": "armandi 0.142", "scores": {"class_score": 0.1424560546875}, "domain": "pixel"}, {"position": {"minX": 229.25, "minY": 436.25, "maxX": 279.25, "maxY": 473.25}, "class_id": 4, "box_caption": "armandi 0.142", "scores": {"class_score": 0.142333984375}, "domain": "pixel"}, {"position": {"minX": 159.125, "minY": 280.5, "maxX": 213.875, "maxY": 362.0}, "class_id": 0, "box_caption": "Boerner 0.138", "scores": {"class_score": 0.13818359375}, "domain": "pixel"}, {"position": {"minX": 236.625, "minY": 361.25, "maxX": 269.5, "maxY": 403.25}, "class_id": 1, "box_caption": "Leconte 0.134", "scores": {"class_score": 0.1339111328125}, "domain": "pixel"}, {"position": {"minX": 239.5, "minY": 359.75, "maxX": 266.25, "maxY": 402.25}, "class_id": 0, "box_caption": "Boerner 0.133", "scores": {"class_score": 0.133056640625}, "domain": "pixel"}, {"position": {"minX": 321.75, "minY": 441.5, "maxX": 375.25, "maxY": 474.0}, "class_id": 5, "box_caption": "coleoptera 0.133", "scores": {"class_score": 0.1329345703125}, "domain": "pixel"}, {"position": {"minX": 240.25, "minY": 358.5, "maxX": 268.5, "maxY": 405.0}, "class_id": 6, "box_caption": "linnaeus 0.113", "scores": {"class_score": 0.1134033203125}, "domain": "pixel"}, {"position": {"minX": 293.75, "minY": 299.5, "maxX": 313.25, "maxY": 328.0}, "class_id": 3, "box_caption": "acuminatus 0.111", "scores": {"class_score": 0.11053466796875}, "domain": "pixel"}, {"position": {"minX": 230.5, "minY": 436.25, "maxX": 280.75, "maxY": 473.25}, "class_id": 5, "box_caption": "coleoptera 0.110", "scores": {"class_score": 0.1104736328125}, "domain": "pixel"}, {"position": {"minX": 291.25, "minY": 295.25, "maxX": 317.75, "maxY": 329.25}, "class_id": 5, "box_caption": "coleoptera 0.108", "scores": {"class_score": 0.10809326171875}, "domain": "pixel"}, {"position": {"minX": 240.25, "minY": 358.5, "maxX": 268.5, "maxY": 405.0}, "class_id": 3, "box_caption": "acuminatus 0.106", "scores": {"class_score": 0.10565185546875}, "domain": "pixel"}, {"position": {"minX": 238.25, "minY": 361.5, "maxX": 267.5, "maxY": 403.0}, "class_id": 2, "box_caption": "Linnaeus 0.094", "scores": {"class_score": 0.09405517578125}, "domain": "pixel"}, {"position": {"minX": 294.25, "minY": 296.5, "maxX": 314.25, "maxY": 329.5}, "class_id": 6, "box_caption": "linnaeus 0.090", "scores": {"class_score": 0.08953857421875}, "domain": "pixel"}, {"position": {"minX": 293.75, "minY": 298.25, "maxX": 314.75, "maxY": 327.75}, "class_id": 0, "box_caption": "Boerner 0.087", "scores": {"class_score": 0.08746337890625}, "domain": "pixel"}, {"position": {"minX": 232.0, "minY": 436.25, "maxX": 281.0, "maxY": 472.25}, "class_id": 6, "box_caption": "linnaeus 0.085", "scores": {"class_score": 0.0850830078125}, "domain": "pixel"}, {"position": {"minX": 117.25, "minY": 293.0, "maxX": 134.25, "maxY": 308.0}, "class_id": 5, "box_caption": "coleoptera 0.083", "scores": {"class_score": 0.0830078125}, "domain": "pixel"}, {"position": {"minX": 229.25, "minY": 436.25, "maxX": 279.25, "maxY": 473.25}, "class_id": 2, "box_caption": "Linnaeus 0.081", "scores": {"class_score": 0.080810546875}, "domain": "pixel"}, {"position": {"minX": 159.125, "minY": 280.5, "maxX": 213.875, "maxY": 362.0}, "class_id": 4, "box_caption": "armandi 0.079", "scores": {"class_score": 0.0792236328125}, "domain": "pixel"}, {"position": {"minX": 395.0, "minY": 340.0, "maxX": 431.0, "maxY": 414.0}, "class_id": 2, "box_caption": "Linnaeus 0.078", "scores": {"class_score": 0.07781982421875}, "domain": "pixel"}, {"position": {"minX": 290.25, "minY": 298.5, "maxX": 315.25, "maxY": 328.5}, "class_id": 2, "box_caption": "Linnaeus 0.078", "scores": {"class_score": 0.07769775390625}, "domain": "pixel"}, {"position": {"minX": 244.5, "minY": 557.5, "maxX": 321.5, "maxY": 617.5}, "class_id": 4, "box_caption": "armandi 0.076", "scores": {"class_score": 0.07586669921875}, "domain": "pixel"}, {"position": {"minX": 253.125, "minY": 548.0, "maxX": 310.0, "maxY": 622.0}, "class_id": 0, "box_caption": "Boerner 0.076", "scores": {"class_score": 0.07574462890625}, "domain": "pixel"}, {"position": {"minX": 321.75, "minY": 441.5, "maxX": 375.25, "maxY": 474.0}, "class_id": 6, "box_caption": "linnaeus 0.072", "scores": {"class_score": 0.07220458984375}, "domain": "pixel"}, {"position": {"minX": 324.0, "minY": 441.75, "maxX": 371.5, "maxY": 474.75}, "class_id": 2, "box_caption": "Linnaeus 0.070", "scores": {"class_score": 0.06988525390625}, "domain": "pixel"}, {"position": {"minX": 392.25, "minY": 341.75, "maxX": 434.25, "maxY": 411.75}, "class_id": 6, "box_caption": "linnaeus 0.068", "scores": {"class_score": 0.0684814453125}, "domain": "pixel"}, {"position": {"minX": 155.375, "minY": 261.5, "maxX": 217.625, "maxY": 382.5}, "class_id": 2, "box_caption": "Linnaeus 0.068", "scores": {"class_score": 0.0684814453125}, "domain": "pixel"}, {"position": {"minX": 155.375, "minY": 261.5, "maxX": 217.625, "maxY": 382.5}, "class_id": 4, "box_caption": "armandi 0.066", "scores": {"class_score": 0.06640625}, "domain": "pixel"}, {"position": {"minX": 153.0, "minY": 277.75, "maxX": 220.0, "maxY": 368.75}, "class_id": 6, "box_caption": "linnaeus 0.060", "scores": {"class_score": 0.059539794921875}, "domain": "pixel"}, {"position": {"minX": 293.75, "minY": 298.25, "maxX": 314.75, "maxY": 327.75}, "class_id": 1, "box_caption": "Leconte 0.057", "scores": {"class_score": 0.056884765625}, "domain": "pixel"}, {"position": {"minX": 393.75, "minY": 339.75, "maxX": 431.25, "maxY": 416.25}, "class_id": 5, "box_caption": "coleoptera 0.052", "scores": {"class_score": 0.051971435546875}, "domain": "pixel"}, {"position": {"minX": 321.75, "minY": 441.5, "maxX": 375.25, "maxY": 474.0}, "class_id": 3, "box_caption": "acuminatus 0.051", "scores": {"class_score": 0.05096435546875}, "domain": "pixel"}, {"position": {"minX": 232.0, "minY": 436.25, "maxX": 281.0, "maxY": 472.25}, "class_id": 3, "box_caption": "acuminatus 0.048", "scores": {"class_score": 0.048126220703125}, "domain": "pixel"}, {"position": {"minX": 251.875, "minY": 561.5, "maxX": 306.25, "maxY": 625.5}, "class_id": 1, "box_caption": "Leconte 0.047", "scores": {"class_score": 0.046539306640625}, "domain": "pixel"}, {"position": {"minX": 393.0, "minY": 342.5, "maxX": 431.0, "maxY": 406.5}, "class_id": 3, "box_caption": "acuminatus 0.047", "scores": {"class_score": 0.0465087890625}, "domain": "pixel"}, {"position": {"minX": 244.5, "minY": 557.5, "maxX": 321.5, "maxY": 617.5}, "class_id": 6, "box_caption": "linnaeus 0.046", "scores": {"class_score": 0.045562744140625}, "domain": "pixel"}, {"position": {"minX": 239.125, "minY": 439.75, "maxX": 275.75, "maxY": 469.25}, "class_id": 4, "box_caption": "armandi 0.045", "scores": {"class_score": 0.04510498046875}, "domain": "pixel"}, {"position": {"minX": 239.125, "minY": 439.75, "maxX": 275.75, "maxY": 469.25}, "class_id": 1, "box_caption": "Leconte 0.044", "scores": {"class_score": 0.044158935546875}, "domain": "pixel"}, {"position": {"minX": 117.25, "minY": 293.0, "maxX": 134.25, "maxY": 308.0}, "class_id": 3, "box_caption": "acuminatus 0.042", "scores": {"class_score": 0.041778564453125}, "domain": "pixel"}, {"position": {"minX": 395.0, "minY": 351.0, "maxX": 430.0, "maxY": 397.5}, "class_id": 0, "box_caption": "Boerner 0.040", "scores": {"class_score": 0.040313720703125}, "domain": "pixel"}, {"position": {"minX": 159.0, "minY": 289.5, "maxX": 202.25, "maxY": 345.0}, "class_id": 1, "box_caption": "Leconte 0.040", "scores": {"class_score": 0.040191650390625}, "domain": "pixel"}, {"position": {"minX": 244.5, "minY": 557.5, "maxX": 321.5, "maxY": 617.5}, "class_id": 2, "box_caption": "Linnaeus 0.037", "scores": {"class_score": 0.037353515625}, "domain": "pixel"}, {"position": {"minX": 395.0, "minY": 351.0, "maxX": 430.0, "maxY": 397.5}, "class_id": 1, "box_caption": "Leconte 0.037", "scores": {"class_score": 0.036712646484375}, "domain": "pixel"}, {"position": {"minX": 239.125, "minY": 439.75, "maxX": 275.75, "maxY": 469.25}, "class_id": 2, "box_caption": "Linnaeus 0.036", "scores": {"class_score": 0.036102294921875}, "domain": "pixel"}, {"position": {"minX": 114.375, "minY": 293.25, "maxX": 134.875, "maxY": 310.25}, "class_id": 4, "box_caption": "armandi 0.034", "scores": {"class_score": 0.034332275390625}, "domain": "pixel"}, {"position": {"minX": 236.75, "minY": 436.75, "maxX": 273.5, "maxY": 471.75}, "class_id": 0, "box_caption": "Boerner 0.033", "scores": {"class_score": 0.03253173828125}, "domain": "pixel"}, {"position": {"minX": 155.375, "minY": 261.5, "maxX": 217.625, "maxY": 382.5}, "class_id": 5, "box_caption": "coleoptera 0.031", "scores": {"class_score": 0.03143310546875}, "domain": "pixel"}, {"position": {"minX": 244.5, "minY": 557.5, "maxX": 321.5, "maxY": 617.5}, "class_id": 5, "box_caption": "coleoptera 0.031", "scores": {"class_score": 0.03131103515625}, "domain": "pixel"}, {"position": {"minX": 117.25, "minY": 293.0, "maxX": 134.25, "maxY": 308.0}, "class_id": 6, "box_caption": "linnaeus 0.027", "scores": {"class_score": 0.026641845703125}, "domain": "pixel"}, {"position": {"minX": 160.125, "minY": 288.5, "maxX": 202.375, "maxY": 351.5}, "class_id": 0, "box_caption": "Boerner 0.025", "scores": {"class_score": 0.0251007080078125}, "domain": "pixel"}, {"position": {"minX": 155.375, "minY": 261.5, "maxX": 217.625, "maxY": 382.5}, "class_id": 3, "box_caption": "acuminatus 0.024", "scores": {"class_score": 0.02435302734375}, "domain": "pixel"}, {"position": {"minX": 239.125, "minY": 439.75, "maxX": 275.75, "maxY": 469.25}, "class_id": 5, "box_caption": "coleoptera 0.024", "scores": {"class_score": 0.0235595703125}, "domain": "pixel"}, {"position": {"minX": 395.0, "minY": 351.0, "maxX": 430.0, "maxY": 397.5}, "class_id": 5, "box_caption": "coleoptera 0.023", "scores": {"class_score": 0.0229644775390625}, "domain": "pixel"}, {"position": {"minX": 233.25, "minY": 568.0, "maxX": 295.75, "maxY": 609.0}, "class_id": 1, "box_caption": "Leconte 0.023", "scores": {"class_score": 0.0226898193359375}, "domain": "pixel"}, {"position": {"minX": 153.0, "minY": 295.25, "maxX": 213.0, "maxY": 370.25}, "class_id": 2, "box_caption": "Linnaeus 0.022", "scores": {"class_score": 0.022430419921875}, "domain": "pixel"}, {"position": {"minX": 395.0, "minY": 351.0, "maxX": 430.0, "maxY": 397.5}, "class_id": 6, "box_caption": "linnaeus 0.021", "scores": {"class_score": 0.02093505859375}, "domain": "pixel"}, {"position": {"minX": 328.75, "minY": 440.25, "maxX": 366.25, "maxY": 471.25}, "class_id": 0, "box_caption": "Boerner 0.021", "scores": {"class_score": 0.0205078125}, "domain": "pixel"}, {"position": {"minX": 334.5, "minY": 445.75, "maxX": 371.0, "maxY": 469.25}, "class_id": 1, "box_caption": "Leconte 0.020", "scores": {"class_score": 0.0201263427734375}, "domain": "pixel"}, {"position": {"minX": 244.25, "minY": 556.0, "maxX": 321.75, "maxY": 619.0}, "class_id": 3, "box_caption": "acuminatus 0.020", "scores": {"class_score": 0.0196075439453125}, "domain": "pixel"}, {"position": {"minX": 261.5, "minY": 548.5, "maxX": 320.0, "maxY": 606.5}, "class_id": 1, "box_caption": "Leconte 0.019", "scores": {"class_score": 0.0193328857421875}, "domain": "pixel"}, {"position": {"minX": 168.0, "minY": 278.25, "maxX": 221.5, "maxY": 344.25}, "class_id": 1, "box_caption": "Leconte 0.018", "scores": {"class_score": 0.018096923828125}, "domain": "pixel"}, {"position": {"minX": 491.75, "minY": -17.53125, "maxX": 517.5, "maxY": 138.375}, "class_id": 0, "box_caption": "Boerner 0.017", "scores": {"class_score": 0.0174713134765625}, "domain": "pixel"}, {"position": {"minX": 491.75, "minY": -17.53125, "maxX": 517.5, "maxY": 138.375}, "class_id": 1, "box_caption": "Leconte 0.016", "scores": {"class_score": 0.0159912109375}, "domain": "pixel"}, {"position": {"minX": 113.125, "minY": 286.75, "maxX": 133.375, "maxY": 311.25}, "class_id": 5, "box_caption": "coleoptera 0.016", "scores": {"class_score": 0.015838623046875}, "domain": "pixel"}, {"position": {"minX": 233.25, "minY": 568.0, "maxX": 295.75, "maxY": 609.0}, "class_id": 0, "box_caption": "Boerner 0.016", "scores": {"class_score": 0.0157318115234375}, "domain": "pixel"}, {"position": {"minX": 242.5, "minY": 361.25, "maxX": 271.5, "maxY": 393.25}, "class_id": 5, "box_caption": "coleoptera 0.015", "scores": {"class_score": 0.01532745361328125}, "domain": "pixel"}, {"position": {"minX": 160.25, "minY": 269.5, "maxX": 212.0, "maxY": 338.0}, "class_id": 1, "box_caption": "Leconte 0.015", "scores": {"class_score": 0.0148468017578125}, "domain": "pixel"}, {"position": {"minX": 379.75, "minY": 354.5, "maxX": 430.25, "maxY": 402.0}, "class_id": 1, "box_caption": "Leconte 0.014", "scores": {"class_score": 0.01445770263671875}, "domain": "pixel"}, {"position": {"minX": 491.75, "minY": -17.53125, "maxX": 517.5, "maxY": 138.375}, "class_id": 2, "box_caption": "Linnaeus 0.014", "scores": {"class_score": 0.01416015625}, "domain": "pixel"}, {"position": {"minX": 288.25, "minY": 299.75, "maxX": 320.75, "maxY": 327.75}, "class_id": 6, "box_caption": "linnaeus 0.013", "scores": {"class_score": 0.01326751708984375}, "domain": "pixel"}, {"position": {"minX": 147.75, "minY": 289.25, "maxX": 212.75, "maxY": 359.25}, "class_id": 3, "box_caption": "acuminatus 0.013", "scores": {"class_score": 0.01284027099609375}, "domain": "pixel"}, {"position": {"minX": 145.5, "minY": 298.5, "maxX": 195.0, "maxY": 350.0}, "class_id": 1, "box_caption": "Leconte 0.013", "scores": {"class_score": 0.01279449462890625}, "domain": "pixel"}, {"position": {"minX": 630.5, "minY": 121.125, "maxX": 632.5, "maxY": 218.625}, "class_id": 1, "box_caption": "Leconte 0.013", "scores": {"class_score": 0.01273345947265625}, "domain": "pixel"}, {"position": {"minX": 327.25, "minY": 442.5, "maxX": 362.25, "maxY": 470.5}, "class_id": 5, "box_caption": "coleoptera 0.013", "scores": {"class_score": 0.012725830078125}, "domain": "pixel"}, {"position": {"minX": 392.75, "minY": 8.1875, "maxX": 581.0, "maxY": 142.75}, "class_id": 1, "box_caption": "Leconte 0.012", "scores": {"class_score": 0.012420654296875}, "domain": "pixel"}, {"position": {"minX": 358.0, "minY": -135.375, "maxX": 681.0, "maxY": 299.5}, "class_id": 0, "box_caption": "Boerner 0.012", "scores": {"class_score": 0.01241302490234375}, "domain": "pixel"}, {"position": {"minX": 114.375, "minY": 293.25, "maxX": 134.875, "maxY": 310.25}, "class_id": 2, "box_caption": "Linnaeus 0.012", "scores": {"class_score": 0.01236724853515625}, "domain": "pixel"}, {"position": {"minX": 293.75, "minY": 307.5, "maxX": 312.25, "maxY": 329.5}, "class_id": 5, "box_caption": "coleoptera 0.012", "scores": {"class_score": 0.0123138427734375}, "domain": "pixel"}, {"position": {"minX": 327.5, "minY": 433.5, "maxX": 370.5, "maxY": 480.0}, "class_id": 1, "box_caption": "Leconte 0.012", "scores": {"class_score": 0.0122833251953125}, "domain": "pixel"}, {"position": {"minX": 358.0, "minY": -135.375, "maxX": 681.0, "maxY": 299.5}, "class_id": 1, "box_caption": "Leconte 0.012", "scores": {"class_score": 0.01177978515625}, "domain": "pixel"}, {"position": {"minX": 502.0, "minY": 38.0, "maxX": 537.0, "maxY": 110.125}, "class_id": 1, "box_caption": "Leconte 0.012", "scores": {"class_score": 0.01177215576171875}, "domain": "pixel"}, {"position": {"minX": 241.75, "minY": 362.75, "maxX": 271.25, "maxY": 391.25}, "class_id": 4, "box_caption": "armandi 0.012", "scores": {"class_score": 0.01154327392578125}, "domain": "pixel"}, {"position": {"minX": 334.5, "minY": 445.75, "maxX": 371.0, "maxY": 469.25}, "class_id": 0, "box_caption": "Boerner 0.011", "scores": {"class_score": 0.01117706298828125}, "domain": "pixel"}, {"position": {"minX": 159.0, "minY": 289.5, "maxX": 202.25, "maxY": 345.0}, "class_id": 4, "box_caption": "armandi 0.011", "scores": {"class_score": 0.010833740234375}, "domain": "pixel"}, {"position": {"minX": 241.75, "minY": 362.75, "maxX": 271.25, "maxY": 391.25}, "class_id": 3, "box_caption": "acuminatus 0.010", "scores": {"class_score": 0.01036834716796875}, "domain": "pixel"}, {"position": {"minX": 290.75, "minY": 294.25, "maxX": 316.75, "maxY": 330.75}, "class_id": 3, "box_caption": "acuminatus 0.010", "scores": {"class_score": 0.0103302001953125}, "domain": "pixel"}, {"position": {"minX": 396.0, "minY": 362.0, "maxX": 433.0, "maxY": 405.0}, "class_id": 4, "box_caption": "armandi 0.010", "scores": {"class_score": 0.01023101806640625}, "domain": "pixel"}, {"position": {"minX": 116.625, "minY": 292.5, "maxX": 138.875, "maxY": 312.0}, "class_id": 5, "box_caption": "coleoptera 0.010", "scores": {"class_score": 0.01015472412109375}, "domain": "pixel"}, {"position": {"minX": 334.5, "minY": 445.75, "maxX": 371.0, "maxY": 469.25}, "class_id": 5, "box_caption": "coleoptera 0.010", "scores": {"class_score": 0.0101470947265625}, "domain": "pixel"}, {"position": {"minX": 441.5, "minY": 57.0, "maxX": 742.5, "maxY": 219.25}, "class_id": 1, "box_caption": "Leconte 0.010", "scores": {"class_score": 0.01013946533203125}, "domain": "pixel"}, {"position": {"minX": 478.0, "minY": 75.8125, "maxX": 578.0, "maxY": 100.6875}, "class_id": 2, "box_caption": "Linnaeus 0.010", "scores": {"class_score": 0.01001739501953125}, "domain": "pixel"}, {"position": {"minX": 223.375, "minY": 443.0, "maxX": 267.25, "maxY": 470.0}, "class_id": 1, "box_caption": "Leconte 0.010", "scores": {"class_score": 0.009979248046875}, "domain": "pixel"}, {"position": {"minX": 261.0, "minY": 551.0, "maxX": 323.5, "maxY": 605.0}, "class_id": 0, "box_caption": "Boerner 0.010", "scores": {"class_score": 0.009979248046875}, "domain": "pixel"}, {"position": {"minX": 478.0, "minY": 75.8125, "maxX": 578.0, "maxY": 100.6875}, "class_id": 1, "box_caption": "Leconte 0.010", "scores": {"class_score": 0.00991058349609375}, "domain": "pixel"}, {"position": {"minX": 158.0, "minY": 279.5, "maxX": 204.5, "maxY": 357.0}, "class_id": 5, "box_caption": "coleoptera 0.010", "scores": {"class_score": 0.00986480712890625}, "domain": "pixel"}, {"position": {"minX": 334.5, "minY": 445.75, "maxX": 371.0, "maxY": 469.25}, "class_id": 4, "box_caption": "armandi 0.010", "scores": {"class_score": 0.0098419189453125}, "domain": "pixel"}, {"position": {"minX": 117.25, "minY": 293.0, "maxX": 134.25, "maxY": 308.0}, "class_id": 0, "box_caption": "Boerner 0.010", "scores": {"class_score": 0.0098114013671875}, "domain": "pixel"}, {"position": {"minX": 73.75, "minY": 572.5, "maxX": 188.25, "maxY": 605.5}, "class_id": 1, "box_caption": "Leconte 0.010", "scores": {"class_score": 0.00958251953125}, "domain": "pixel"}, {"position": {"minX": 153.0, "minY": 295.25, "maxX": 213.0, "maxY": 370.25}, "class_id": 5, "box_caption": "coleoptera 0.010", "scores": {"class_score": 0.00954437255859375}, "domain": "pixel"}, {"position": {"minX": 334.5, "minY": 445.75, "maxX": 371.0, "maxY": 469.25}, "class_id": 2, "box_caption": "Linnaeus 0.010", "scores": {"class_score": 0.00951385498046875}, "domain": "pixel"}, {"position": {"minX": 160.25, "minY": 276.25, "maxX": 212.75, "maxY": 354.75}, "class_id": 2, "box_caption": "Linnaeus 0.009", "scores": {"class_score": 0.00933837890625}, "domain": "pixel"}, {"position": {"minX": 169.0, "minY": 282.0, "maxX": 218.5, "maxY": 353.0}, "class_id": 6, "box_caption": "linnaeus 0.009", "scores": {"class_score": 0.009033203125}, "domain": "pixel"}, {"position": {"minX": 396.0, "minY": 362.0, "maxX": 433.0, "maxY": 405.0}, "class_id": 2, "box_caption": "Linnaeus 0.009", "scores": {"class_score": 0.0090179443359375}, "domain": "pixel"}, {"position": {"minX": 531.0, "minY": 120.9375, "maxX": 623.0, "maxY": 125.3125}, "class_id": 2, "box_caption": "Linnaeus 0.009", "scores": {"class_score": 0.00897979736328125}, "domain": "pixel"}, {"position": {"minX": 243.0, "minY": 359.75, "maxX": 268.25, "maxY": 393.75}, "class_id": 1, "box_caption": "Leconte 0.009", "scores": {"class_score": 0.00887298583984375}, "domain": "pixel"}, {"position": {"minX": 171.375, "minY": 299.0, "maxX": 209.625, "maxY": 347.0}, "class_id": 0, "box_caption": "Boerner 0.009", "scores": {"class_score": 0.008758544921875}, "domain": "pixel"}, {"position": {"minX": 369.5, "minY": -51.9375, "maxX": 640.5, "maxY": 225.75}, "class_id": 1, "box_caption": "Leconte 0.009", "scores": {"class_score": 0.00870513916015625}, "domain": "pixel"}, {"position": {"minX": 531.0, "minY": 120.9375, "maxX": 623.0, "maxY": 125.3125}, "class_id": 6, "box_caption": "linnaeus 0.009", "scores": {"class_score": 0.0086517333984375}, "domain": "pixel"}, {"position": {"minX": 241.75, "minY": 362.75, "maxX": 271.25, "maxY": 391.25}, "class_id": 2, "box_caption": "Linnaeus 0.009", "scores": {"class_score": 0.00859832763671875}, "domain": "pixel"}, {"position": {"minX": 145.5, "minY": 298.5, "maxX": 195.0, "maxY": 350.0}, "class_id": 0, "box_caption": "Boerner 0.008", "scores": {"class_score": 0.008392333984375}, "domain": "pixel"}, {"position": {"minX": 289.25, "minY": 293.75, "maxX": 314.25, "maxY": 322.25}, "class_id": 4, "box_caption": "armandi 0.008", "scores": {"class_score": 0.0082244873046875}, "domain": "pixel"}, {"position": {"minX": 160.25, "minY": 269.5, "maxX": 212.0, "maxY": 338.0}, "class_id": 0, "box_caption": "Boerner 0.008", "scores": {"class_score": 0.00821685791015625}, "domain": "pixel"}, {"position": {"minX": 117.25, "minY": 293.0, "maxX": 134.25, "maxY": 308.0}, "class_id": 1, "box_caption": "Leconte 0.008", "scores": {"class_score": 0.00806427001953125}, "domain": "pixel"}, {"position": {"minX": 240.875, "minY": 570.5, "maxX": 308.0, "maxY": 617.5}, "class_id": 0, "box_caption": "Boerner 0.008", "scores": {"class_score": 0.0080108642578125}, "domain": "pixel"}, {"position": {"minX": 117.3125, "minY": 292.0, "maxX": 139.75, "maxY": 311.5}, "class_id": 3, "box_caption": "acuminatus 0.008", "scores": {"class_score": 0.00787353515625}, "domain": "pixel"}, {"position": {"minX": 478.0, "minY": 75.8125, "maxX": 578.0, "maxY": 100.6875}, "class_id": 0, "box_caption": "Boerner 0.008", "scores": {"class_score": 0.007724761962890625}, "domain": "pixel"}, {"position": {"minX": 553.0, "minY": 75.5, "maxX": 636.0, "maxY": 195.0}, "class_id": 1, "box_caption": "Leconte 0.008", "scores": {"class_score": 0.00771331787109375}, "domain": "pixel"}, {"position": {"minX": 385.0, "minY": 349.75, "maxX": 424.0, "maxY": 406.25}, "class_id": 0, "box_caption": "Boerner 0.008", "scores": {"class_score": 0.007671356201171875}, "domain": "pixel"}, {"position": {"minX": 266.5, "minY": 562.0, "maxX": 314.5, "maxY": 640.0}, "class_id": 1, "box_caption": "Leconte 0.008", "scores": {"class_score": 0.007572174072265625}, "domain": "pixel"}, {"position": {"minX": 118.9375, "minY": 284.0, "maxX": 141.625, "maxY": 314.0}, "class_id": 5, "box_caption": "coleoptera 0.008", "scores": {"class_score": 0.007549285888671875}, "domain": "pixel"}, {"position": {"minX": 147.0, "minY": 299.25, "maxX": 203.25, "maxY": 371.25}, "class_id": 1, "box_caption": "Leconte 0.008", "scores": {"class_score": 0.00754547119140625}, "domain": "pixel"}, {"position": {"minX": 289.75, "minY": 289.5, "maxX": 313.75, "maxY": 322.5}, "class_id": 0, "box_caption": "Boerner 0.007", "scores": {"class_score": 0.00725555419921875}, "domain": "pixel"}, {"position": {"minX": 235.5, "minY": 419.5, "maxX": 284.0, "maxY": 475.5}, "class_id": 1, "box_caption": "Leconte 0.007", "scores": {"class_score": 0.007205963134765625}, "domain": "pixel"}, {"position": {"minX": 248.375, "minY": 565.0, "maxX": 326.0, "maxY": 641.0}, "class_id": 1, "box_caption": "Leconte 0.007", "scores": {"class_score": 0.007144927978515625}, "domain": "pixel"}, {"position": {"minX": 289.75, "minY": 289.5, "maxX": 313.75, "maxY": 322.5}, "class_id": 5, "box_caption": "coleoptera 0.007", "scores": {"class_score": 0.007080078125}, "domain": "pixel"}, {"position": {"minX": 115.875, "minY": 288.75, "maxX": 135.25, "maxY": 318.25}, "class_id": 5, "box_caption": "coleoptera 0.007", "scores": {"class_score": 0.006984710693359375}, "domain": "pixel"}, {"position": {"minX": 113.125, "minY": 286.75, "maxX": 133.375, "maxY": 311.25}, "class_id": 6, "box_caption": "linnaeus 0.007", "scores": {"class_score": 0.006908416748046875}, "domain": "pixel"}, {"position": {"minX": 136.25, "minY": 293.5, "maxX": 187.0, "maxY": 332.5}, "class_id": 1, "box_caption": "Leconte 0.007", "scores": {"class_score": 0.006847381591796875}, "domain": "pixel"}, {"position": {"minX": 504.75, "minY": 35.375, "maxX": 546.0, "maxY": 71.1875}, "class_id": 1, "box_caption": "Leconte 0.007", "scores": {"class_score": 0.00682830810546875}, "domain": "pixel"}, {"position": {"minX": 327.5, "minY": 433.5, "maxX": 370.5, "maxY": 480.0}, "class_id": 0, "box_caption": "Boerner 0.007", "scores": {"class_score": 0.0068206787109375}, "domain": "pixel"}, {"position": {"minX": 358.0, "minY": -135.375, "maxX": 681.0, "maxY": 299.5}, "class_id": 5, "box_caption": "coleoptera 0.007", "scores": {"class_score": 0.006778717041015625}, "domain": "pixel"}, {"position": {"minX": 639.5, "minY": 183.0, "maxX": 649.5, "maxY": 198.0}, "class_id": 1, "box_caption": "Leconte 0.007", "scores": {"class_score": 0.006710052490234375}, "domain": "pixel"}, {"position": {"minX": 167.125, "minY": 286.0, "maxX": 218.625, "maxY": 358.0}, "class_id": 5, "box_caption": "coleoptera 0.007", "scores": {"class_score": 0.006679534912109375}, "domain": "pixel"}, {"position": {"minX": 388.5, "minY": 334.5, "maxX": 427.5, "maxY": 381.5}, "class_id": 1, "box_caption": "Leconte 0.007", "scores": {"class_score": 0.00664520263671875}, "domain": "pixel"}, {"position": {"minX": 453.0, "minY": 55.78125, "maxX": 696.0, "maxY": 124.125}, "class_id": 1, "box_caption": "Leconte 0.007", "scores": {"class_score": 0.006633758544921875}, "domain": "pixel"}, {"position": {"minX": 233.25, "minY": 568.0, "maxX": 295.75, "maxY": 609.0}, "class_id": 4, "box_caption": "armandi 0.007", "scores": {"class_score": 0.00656890869140625}, "domain": "pixel"}, {"position": {"minX": 241.75, "minY": 362.75, "maxX": 271.25, "maxY": 391.25}, "class_id": 6, "box_caption": "linnaeus 0.007", "scores": {"class_score": 0.006557464599609375}, "domain": "pixel"}, {"position": {"minX": 161.25, "minY": 305.5, "maxX": 214.25, "maxY": 378.0}, "class_id": 1, "box_caption": "Leconte 0.007", "scores": {"class_score": 0.006511688232421875}, "domain": "pixel"}, {"position": {"minX": 441.5, "minY": 57.0, "maxX": 742.5, "maxY": 219.25}, "class_id": 0, "box_caption": "Boerner 0.006", "scores": {"class_score": 0.006473541259765625}, "domain": "pixel"}, {"position": {"minX": 388.5, "minY": 334.5, "maxX": 427.5, "maxY": 381.5}, "class_id": 0, "box_caption": "Boerner 0.006", "scores": {"class_score": 0.006439208984375}, "domain": "pixel"}, {"position": {"minX": 232.75, "minY": 438.25, "maxX": 278.0, "maxY": 482.75}, "class_id": 0, "box_caption": "Boerner 0.006", "scores": {"class_score": 0.006435394287109375}, "domain": "pixel"}, {"position": {"minX": 630.5, "minY": 121.125, "maxX": 632.5, "maxY": 218.625}, "class_id": 6, "box_caption": "linnaeus 0.006", "scores": {"class_score": 0.0063934326171875}, "domain": "pixel"}, {"position": {"minX": 630.5, "minY": 121.125, "maxX": 632.5, "maxY": 218.625}, "class_id": 4, "box_caption": "armandi 0.006", "scores": {"class_score": 0.00632476806640625}, "domain": "pixel"}, {"position": {"minX": 113.125, "minY": 286.75, "maxX": 133.375, "maxY": 311.25}, "class_id": 0, "box_caption": "Boerner 0.006", "scores": {"class_score": 0.00627899169921875}, "domain": "pixel"}, {"position": {"minX": 169.0, "minY": 282.0, "maxX": 218.5, "maxY": 353.0}, "class_id": 3, "box_caption": "acuminatus 0.006", "scores": {"class_score": 0.006252288818359375}, "domain": "pixel"}, {"position": {"minX": 372.75, "minY": -6.78125, "maxX": 539.5, "maxY": 130.75}, "class_id": 1, "box_caption": "Leconte 0.006", "scores": {"class_score": 0.006191253662109375}, "domain": "pixel"}, {"position": {"minX": 159.0, "minY": 289.5, "maxX": 202.25, "maxY": 345.0}, "class_id": 3, "box_caption": "acuminatus 0.006", "scores": {"class_score": 0.006175994873046875}, "domain": "pixel"}, {"position": {"minX": 377.0, "minY": 638.0, "maxX": 427.5, "maxY": 668.0}, "class_id": 1, "box_caption": "Leconte 0.006", "scores": {"class_score": 0.006069183349609375}, "domain": "pixel"}, {"position": {"minX": 327.25, "minY": 442.5, "maxX": 362.25, "maxY": 470.5}, "class_id": 3, "box_caption": "acuminatus 0.006", "scores": {"class_score": 0.005962371826171875}, "domain": "pixel"}, {"position": {"minX": 498.75, "minY": 56.3125, "maxX": 682.5, "maxY": 187.5}, "class_id": 1, "box_caption": "Leconte 0.006", "scores": {"class_score": 0.00579071044921875}, "domain": "pixel"}, {"position": {"minX": 164.625, "minY": 275.75, "maxX": 212.375, "maxY": 337.25}, "class_id": 4, "box_caption": "armandi 0.006", "scores": {"class_score": 0.0057373046875}, "domain": "pixel"}, {"position": {"minX": 113.125, "minY": 286.75, "maxX": 133.375, "maxY": 311.25}, "class_id": 3, "box_caption": "acuminatus 0.006", "scores": {"class_score": 0.00568389892578125}, "domain": "pixel"}, {"position": {"minX": 110.4375, "minY": 296.0, "maxX": 133.75, "maxY": 319.0}, "class_id": 5, "box_caption": "coleoptera 0.006", "scores": {"class_score": 0.00568389892578125}, "domain": "pixel"}, {"position": {"minX": 289.25, "minY": 293.75, "maxX": 314.25, "maxY": 322.25}, "class_id": 1, "box_caption": "Leconte 0.006", "scores": {"class_score": 0.005596160888671875}, "domain": "pixel"}, {"position": {"minX": 285.0, "minY": 295.25, "maxX": 309.5, "maxY": 327.25}, "class_id": 5, "box_caption": "coleoptera 0.006", "scores": {"class_score": 0.00556182861328125}, "domain": "pixel"}, {"position": {"minX": 120.25, "minY": 290.0, "maxX": 142.75, "maxY": 312.0}, "class_id": 4, "box_caption": "armandi 0.006", "scores": {"class_score": 0.005535125732421875}, "domain": "pixel"}, {"position": {"minX": 274.0, "minY": 294.0, "maxX": 313.0, "maxY": 325.5}, "class_id": 0, "box_caption": "Boerner 0.005", "scores": {"class_score": 0.005474090576171875}, "domain": "pixel"}, {"position": {"minX": 507.25, "minY": 14.875, "maxX": 530.0, "maxY": 148.75}, "class_id": 1, "box_caption": "Leconte 0.005", "scores": {"class_score": 0.005435943603515625}, "domain": "pixel"}, {"position": {"minX": 233.25, "minY": 568.0, "maxX": 295.75, "maxY": 609.0}, "class_id": 2, "box_caption": "Linnaeus 0.005", "scores": {"class_score": 0.005435943603515625}, "domain": "pixel"}, {"position": {"minX": 507.25, "minY": 14.875, "maxX": 530.0, "maxY": 148.75}, "class_id": 0, "box_caption": "Boerner 0.005", "scores": {"class_score": 0.0054168701171875}, "domain": "pixel"}, {"position": {"minX": 296.75, "minY": 291.5, "maxX": 337.25, "maxY": 328.0}, "class_id": 0, "box_caption": "Boerner 0.005", "scores": {"class_score": 0.0054168701171875}, "domain": "pixel"}, {"position": {"minX": 245.25, "minY": 433.5, "maxX": 280.25, "maxY": 468.5}, "class_id": 0, "box_caption": "Boerner 0.005", "scores": {"class_score": 0.005367279052734375}, "domain": "pixel"}, {"position": {"minX": 377.0, "minY": 638.0, "maxX": 427.5, "maxY": 668.0}, "class_id": 0, "box_caption": "Boerner 0.005", "scores": {"class_score": 0.0053558349609375}, "domain": "pixel"}, {"position": {"minX": 109.0, "minY": 554.0, "maxX": 154.0, "maxY": 607.0}, "class_id": 1, "box_caption": "Leconte 0.005", "scores": {"class_score": 0.005340576171875}, "domain": "pixel"}, {"position": {"minX": 145.5, "minY": 298.5, "maxX": 195.0, "maxY": 350.0}, "class_id": 4, "box_caption": "armandi 0.005", "scores": {"class_score": 0.005329132080078125}, "domain": "pixel"}, {"position": {"minX": 327.0, "minY": 439.5, "maxX": 361.5, "maxY": 470.5}, "class_id": 6, "box_caption": "linnaeus 0.005", "scores": {"class_score": 0.005290985107421875}, "domain": "pixel"}, {"position": {"minX": 293.75, "minY": 307.5, "maxX": 312.25, "maxY": 329.5}, "class_id": 4, "box_caption": "armandi 0.005", "scores": {"class_score": 0.005279541015625}, "domain": "pixel"}, {"position": {"minX": 599.5, "minY": 83.875, "maxX": 599.5, "maxY": 185.125}, "class_id": 1, "box_caption": "Leconte 0.005", "scores": {"class_score": 0.00527191162109375}, "domain": "pixel"}, {"position": {"minX": 512.0, "minY": 103.125, "maxX": 611.0, "maxY": 107.625}, "class_id": 2, "box_caption": "Linnaeus 0.005", "scores": {"class_score": 0.00522613525390625}, "domain": "pixel"}, {"position": {"minX": 480.0, "minY": 109.0625, "maxX": 709.0, "maxY": 143.625}, "class_id": 1, "box_caption": "Leconte 0.005", "scores": {"class_score": 0.00522613525390625}, "domain": "pixel"}, {"position": {"minX": 512.0, "minY": 103.125, "maxX": 611.0, "maxY": 107.625}, "class_id": 6, "box_caption": "linnaeus 0.005", "scores": {"class_score": 0.0051422119140625}, "domain": "pixel"}, {"position": {"minX": 136.25, "minY": 293.5, "maxX": 187.0, "maxY": 332.5}, "class_id": 0, "box_caption": "Boerner 0.005", "scores": {"class_score": 0.0051422119140625}, "domain": "pixel"}, {"position": {"minX": 502.0, "minY": 38.0, "maxX": 537.0, "maxY": 110.125}, "class_id": 4, "box_caption": "armandi 0.005", "scores": {"class_score": 0.005130767822265625}, "domain": "pixel"}, {"position": {"minX": 334.5, "minY": 445.75, "maxX": 371.0, "maxY": 469.25}, "class_id": 3, "box_caption": "acuminatus 0.005", "scores": {"class_score": 0.005107879638671875}, "domain": "pixel"}, {"position": {"minX": 296.75, "minY": 291.5, "maxX": 337.25, "maxY": 328.0}, "class_id": 4, "box_caption": "armandi 0.005", "scores": {"class_score": 0.00510406494140625}, "domain": "pixel"}, {"position": {"minX": 120.4375, "minY": 296.0, "maxX": 143.25, "maxY": 321.0}, "class_id": 5, "box_caption": "coleoptera 0.005", "scores": {"class_score": 0.0050506591796875}, "domain": "pixel"}, {"position": {"minX": 292.5, "minY": 296.75, "maxX": 316.5, "maxY": 340.25}, "class_id": 1, "box_caption": "Leconte 0.005", "scores": {"class_score": 0.005031585693359375}, "domain": "pixel"}, {"position": {"minX": 296.75, "minY": 291.5, "maxX": 337.25, "maxY": 328.0}, "class_id": 1, "box_caption": "Leconte 0.005", "scores": {"class_score": 0.005016326904296875}, "domain": "pixel"}, {"position": {"minX": 241.75, "minY": 362.75, "maxX": 271.25, "maxY": 391.25}, "class_id": 0, "box_caption": "Boerner 0.005", "scores": {"class_score": 0.0050048828125}, "domain": "pixel"}, {"position": {"minX": 396.0, "minY": 362.0, "maxX": 433.0, "maxY": 405.0}, "class_id": 3, "box_caption": "acuminatus 0.005", "scores": {"class_score": 0.0050048828125}, "domain": "pixel"}, {"position": {"minX": 274.0, "minY": 294.0, "maxX": 313.0, "maxY": 325.5}, "class_id": 1, "box_caption": "Leconte 0.005", "scores": {"class_score": 0.005001068115234375}, "domain": "pixel"}, {"position": {"minX": 472.25, "minY": -17.0625, "maxX": 499.25, "maxY": 122.6875}, "class_id": 1, "box_caption": "Leconte 0.005", "scores": {"class_score": 0.0049285888671875}, "domain": "pixel"}, {"position": {"minX": 427.75, "minY": 2.0, "maxX": 673.0, "maxY": 174.125}, "class_id": 1, "box_caption": "Leconte 0.005", "scores": {"class_score": 0.0048828125}, "domain": "pixel"}, {"position": {"minX": 294.0, "minY": 285.75, "maxX": 319.0, "maxY": 325.75}, "class_id": 0, "box_caption": "Boerner 0.005", "scores": {"class_score": 0.004878997802734375}, "domain": "pixel"}, {"position": {"minX": 630.5, "minY": 121.125, "maxX": 632.5, "maxY": 218.625}, "class_id": 5, "box_caption": "coleoptera 0.005", "scores": {"class_score": 0.00484466552734375}, "domain": "pixel"}, {"position": {"minX": 223.125, "minY": 438.25, "maxX": 266.5, "maxY": 472.25}, "class_id": 6, "box_caption": "linnaeus 0.005", "scores": {"class_score": 0.00479888916015625}, "domain": "pixel"}, {"position": {"minX": 398.5, "minY": 351.5, "maxX": 432.5, "maxY": 395.5}, "class_id": 2, "box_caption": "Linnaeus 0.005", "scores": {"class_score": 0.00478363037109375}, "domain": "pixel"}, {"position": {"minX": 609.0, "minY": 80.75, "maxX": 615.0, "maxY": 167.75}, "class_id": 1, "box_caption": "Leconte 0.005", "scores": {"class_score": 0.0047607421875}, "domain": "pixel"}, {"position": {"minX": 398.5, "minY": 351.5, "maxX": 432.5, "maxY": 395.5}, "class_id": 4, "box_caption": "armandi 0.005", "scores": {"class_score": 0.004749298095703125}, "domain": "pixel"}, {"position": {"minX": 502.0, "minY": 38.0, "maxX": 537.0, "maxY": 110.125}, "class_id": 2, "box_caption": "Linnaeus 0.005", "scores": {"class_score": 0.00469970703125}, "domain": "pixel"}, {"position": {"minX": 118.75, "minY": 545.0, "maxX": 132.125, "maxY": 629.0}, "class_id": 1, "box_caption": "Leconte 0.005", "scores": {"class_score": 0.004669189453125}, "domain": "pixel"}, {"position": {"minX": 294.0, "minY": 285.75, "maxX": 319.0, "maxY": 325.75}, "class_id": 4, "box_caption": "armandi 0.005", "scores": {"class_score": 0.00466156005859375}, "domain": "pixel"}, {"position": {"minX": 159.0, "minY": 289.5, "maxX": 202.25, "maxY": 345.0}, "class_id": 6, "box_caption": "linnaeus 0.005", "scores": {"class_score": 0.00466156005859375}, "domain": "pixel"}, {"position": {"minX": 113.125, "minY": 286.75, "maxX": 133.375, "maxY": 311.25}, "class_id": 1, "box_caption": "Leconte 0.005", "scores": {"class_score": 0.00461578369140625}, "domain": "pixel"}, {"position": {"minX": 584.0, "minY": 89.875, "maxX": 584.0, "maxY": 145.875}, "class_id": 1, "box_caption": "Leconte 0.005", "scores": {"class_score": 0.0045928955078125}, "domain": "pixel"}, {"position": {"minX": 506.5, "minY": 118.3125, "maxX": 734.5, "maxY": 254.75}, "class_id": 1, "box_caption": "Leconte 0.005", "scores": {"class_score": 0.004589080810546875}, "domain": "pixel"}, {"position": {"minX": 162.0, "minY": 320.25, "maxX": 230.75, "maxY": 385.75}, "class_id": 1, "box_caption": "Leconte 0.005", "scores": {"class_score": 0.00457000732421875}, "domain": "pixel"}, {"position": {"minX": 159.0, "minY": 289.5, "maxX": 202.25, "maxY": 345.0}, "class_id": 2, "box_caption": "Linnaeus 0.005", "scores": {"class_score": 0.0045623779296875}, "domain": "pixel"}, {"position": {"minX": 274.0, "minY": 294.0, "maxX": 313.0, "maxY": 325.5}, "class_id": 4, "box_caption": "armandi 0.004", "scores": {"class_score": 0.00447845458984375}, "domain": "pixel"}, {"position": {"minX": 223.375, "minY": 443.0, "maxX": 267.25, "maxY": 470.0}, "class_id": 4, "box_caption": "armandi 0.004", "scores": {"class_score": 0.004474639892578125}, "domain": "pixel"}, {"position": {"minX": 542.5, "minY": 41.34375, "maxX": 568.5, "maxY": 124.125}, "class_id": 1, "box_caption": "Leconte 0.004", "scores": {"class_score": 0.004467010498046875}, "domain": "pixel"}, {"position": {"minX": 377.0, "minY": 638.0, "maxX": 427.5, "maxY": 668.0}, "class_id": 4, "box_caption": "armandi 0.004", "scores": {"class_score": 0.004421234130859375}, "domain": "pixel"}, {"position": {"minX": 528.0, "minY": 32.5625, "maxX": 555.0, "maxY": 112.4375}, "class_id": 1, "box_caption": "Leconte 0.004", "scores": {"class_score": 0.00438690185546875}, "domain": "pixel"}, {"position": {"minX": 110.4375, "minY": 296.0, "maxX": 133.75, "maxY": 319.0}, "class_id": 4, "box_caption": "armandi 0.004", "scores": {"class_score": 0.00437164306640625}, "domain": "pixel"}, {"position": {"minX": 76.5, "minY": 559.0, "maxX": 150.75, "maxY": 620.0}, "class_id": 1, "box_caption": "Leconte 0.004", "scores": {"class_score": 0.004360198974609375}, "domain": "pixel"}, {"position": {"minX": 102.5, "minY": 289.25, "maxX": 135.75, "maxY": 311.75}, "class_id": 5, "box_caption": "coleoptera 0.004", "scores": {"class_score": 0.004352569580078125}, "domain": "pixel"}, {"position": {"minX": 223.375, "minY": 443.0, "maxX": 267.25, "maxY": 470.0}, "class_id": 5, "box_caption": "coleoptera 0.004", "scores": {"class_score": 0.00433349609375}, "domain": "pixel"}, {"position": {"minX": 261.5, "minY": 548.5, "maxX": 320.0, "maxY": 606.5}, "class_id": 4, "box_caption": "armandi 0.004", "scores": {"class_score": 0.004268646240234375}, "domain": "pixel"}, {"position": {"minX": 607.0, "minY": 160.5, "maxX": 631.0, "maxY": 214.25}, "class_id": 1, "box_caption": "Leconte 0.004", "scores": {"class_score": 0.00421142578125}, "domain": "pixel"}, {"position": {"minX": 362.75, "minY": 351.25, "maxX": 406.75, "maxY": 393.75}, "class_id": 1, "box_caption": "Leconte 0.004", "scores": {"class_score": 0.004180908203125}, "domain": "pixel"}, {"position": {"minX": 599.5, "minY": 83.875, "maxX": 599.5, "maxY": 185.125}, "class_id": 4, "box_caption": "armandi 0.004", "scores": {"class_score": 0.00417327880859375}, "domain": "pixel"}, {"position": {"minX": 152.125, "minY": 319.5, "maxX": 218.375, "maxY": 367.5}, "class_id": 1, "box_caption": "Leconte 0.004", "scores": {"class_score": 0.0041656494140625}, "domain": "pixel"}, {"position": {"minX": 293.75, "minY": 307.5, "maxX": 312.25, "maxY": 329.5}, "class_id": 6, "box_caption": "linnaeus 0.004", "scores": {"class_score": 0.004154205322265625}, "domain": "pixel"}, {"position": {"minX": 171.375, "minY": 299.0, "maxX": 209.625, "maxY": 347.0}, "class_id": 1, "box_caption": "Leconte 0.004", "scores": {"class_score": 0.004146575927734375}, "domain": "pixel"}, {"position": {"minX": 179.875, "minY": 288.75, "maxX": 219.125, "maxY": 353.25}, "class_id": 1, "box_caption": "Leconte 0.004", "scores": {"class_score": 0.004138946533203125}, "domain": "pixel"}, {"position": {"minX": 237.5, "minY": 355.5, "maxX": 267.75, "maxY": 387.5}, "class_id": 5, "box_caption": "coleoptera 0.004", "scores": {"class_score": 0.004116058349609375}, "domain": "pixel"}, {"position": {"minX": 393.0, "minY": 642.0, "maxX": 425.5, "maxY": 662.0}, "class_id": 4, "box_caption": "armandi 0.004", "scores": {"class_score": 0.004116058349609375}, "domain": "pixel"}, {"position": {"minX": 599.0, "minY": 184.75, "maxX": 663.0, "maxY": 242.75}, "class_id": 1, "box_caption": "Leconte 0.004", "scores": {"class_score": 0.00409698486328125}, "domain": "pixel"}, {"position": {"minX": 347.5, "minY": 642.0, "maxX": 396.0, "maxY": 673.0}, "class_id": 1, "box_caption": "Leconte 0.004", "scores": {"class_score": 0.004093170166015625}, "domain": "pixel"}, {"position": {"minX": 288.5, "minY": 302.25, "maxX": 315.5, "maxY": 334.25}, "class_id": 5, "box_caption": "coleoptera 0.004", "scores": {"class_score": 0.00408935546875}, "domain": "pixel"}, {"position": {"minX": 289.75, "minY": 289.5, "maxX": 313.75, "maxY": 322.5}, "class_id": 3, "box_caption": "acuminatus 0.004", "scores": {"class_score": 0.0040740966796875}, "domain": "pixel"}, {"position": {"minX": 331.25, "minY": 422.0, "maxX": 382.75, "maxY": 478.0}, "class_id": 1, "box_caption": "Leconte 0.004", "scores": {"class_score": 0.0040740966796875}, "domain": "pixel"}, {"position": {"minX": 233.25, "minY": 568.0, "maxX": 295.75, "maxY": 609.0}, "class_id": 5, "box_caption": "coleoptera 0.004", "scores": {"class_score": 0.00406646728515625}, "domain": "pixel"}, {"position": {"minX": 120.4375, "minY": 296.0, "maxX": 143.25, "maxY": 321.0}, "class_id": 4, "box_caption": "armandi 0.004", "scores": {"class_score": 0.004039764404296875}, "domain": "pixel"}, {"position": {"minX": 572.5, "minY": 58.5, "maxX": 631.5, "maxY": 218.25}, "class_id": 1, "box_caption": "Leconte 0.004", "scores": {"class_score": 0.004016876220703125}, "domain": "pixel"}, {"position": {"minX": 261.0, "minY": 551.0, "maxX": 323.5, "maxY": 605.0}, "class_id": 2, "box_caption": "Linnaeus 0.004", "scores": {"class_score": 0.003997802734375}, "domain": "pixel"}, {"position": {"minX": 427.75, "minY": 2.0, "maxX": 673.0, "maxY": 174.125}, "class_id": 4, "box_caption": "armandi 0.004", "scores": {"class_score": 0.003993988037109375}, "domain": "pixel"}, {"position": {"minX": 388.5, "minY": 334.5, "maxX": 427.5, "maxY": 381.5}, "class_id": 4, "box_caption": "armandi 0.004", "scores": {"class_score": 0.003993988037109375}, "domain": "pixel"}, {"position": {"minX": 327.5, "minY": 433.5, "maxX": 370.5, "maxY": 480.0}, "class_id": 4, "box_caption": "armandi 0.004", "scores": {"class_score": 0.003986358642578125}, "domain": "pixel"}, {"position": {"minX": 584.0, "minY": 89.875, "maxX": 584.0, "maxY": 145.875}, "class_id": 4, "box_caption": "armandi 0.004", "scores": {"class_score": 0.003971099853515625}, "domain": "pixel"}, {"position": {"minX": 578.5, "minY": 171.375, "maxX": 671.5, "maxY": 253.375}, "class_id": 1, "box_caption": "Leconte 0.004", "scores": {"class_score": 0.00396728515625}, "domain": "pixel"}, {"position": {"minX": 292.5, "minY": 296.75, "maxX": 316.5, "maxY": 340.25}, "class_id": 0, "box_caption": "Boerner 0.004", "scores": {"class_score": 0.003963470458984375}, "domain": "pixel"}, {"position": {"minX": 235.5, "minY": 419.5, "maxX": 284.0, "maxY": 475.5}, "class_id": 0, "box_caption": "Boerner 0.004", "scores": {"class_score": 0.00395965576171875}, "domain": "pixel"}, {"position": {"minX": 599.5, "minY": 83.875, "maxX": 599.5, "maxY": 185.125}, "class_id": 6, "box_caption": "linnaeus 0.004", "scores": {"class_score": 0.003955841064453125}, "domain": "pixel"}, {"position": {"minX": 233.25, "minY": 568.0, "maxX": 295.75, "maxY": 609.0}, "class_id": 6, "box_caption": "linnaeus 0.004", "scores": {"class_score": 0.003932952880859375}, "domain": "pixel"}, {"position": {"minX": 237.5, "minY": 355.5, "maxX": 267.75, "maxY": 387.5}, "class_id": 4, "box_caption": "armandi 0.004", "scores": {"class_score": 0.003925323486328125}, "domain": "pixel"}, {"position": {"minX": 301.25, "minY": 423.75, "maxX": 318.75, "maxY": 447.75}, "class_id": 5, "box_caption": "coleoptera 0.004", "scores": {"class_score": 0.0039215087890625}, "domain": "pixel"}, {"position": {"minX": 393.0, "minY": 642.0, "maxX": 425.5, "maxY": 662.0}, "class_id": 5, "box_caption": "coleoptera 0.004", "scores": {"class_score": 0.0039215087890625}, "domain": "pixel"}, {"position": {"minX": 147.0, "minY": 299.25, "maxX": 203.25, "maxY": 371.25}, "class_id": 0, "box_caption": "Boerner 0.004", "scores": {"class_score": 0.003879547119140625}, "domain": "pixel"}, {"position": {"minX": 454.75, "minY": 25.59375, "maxX": 457.75, "maxY": 53.71875}, "class_id": 4, "box_caption": "armandi 0.004", "scores": {"class_score": 0.0038700103759765625}, "domain": "pixel"}, {"position": {"minX": 225.375, "minY": 362.75, "maxX": 262.75, "maxY": 398.75}, "class_id": 1, "box_caption": "Leconte 0.004", "scores": {"class_score": 0.0038661956787109375}, "domain": "pixel"}, {"position": {"minX": 584.0, "minY": 89.875, "maxX": 584.0, "maxY": 145.875}, "class_id": 6, "box_caption": "linnaeus 0.004", "scores": {"class_score": 0.00385284423828125}, "domain": "pixel"}, {"position": {"minX": 120.25, "minY": 290.0, "maxX": 142.75, "maxY": 312.0}, "class_id": 6, "box_caption": "linnaeus 0.004", "scores": {"class_score": 0.0037708282470703125}, "domain": "pixel"}, {"position": {"minX": 168.0, "minY": 278.25, "maxX": 221.5, "maxY": 344.25}, "class_id": 0, "box_caption": "Boerner 0.004", "scores": {"class_score": 0.003765106201171875}, "domain": "pixel"}, {"position": {"minX": 289.75, "minY": 289.5, "maxX": 313.75, "maxY": 322.5}, "class_id": 6, "box_caption": "linnaeus 0.004", "scores": {"class_score": 0.0037517547607421875}, "domain": "pixel"}, {"position": {"minX": 347.5, "minY": 642.0, "maxX": 396.0, "maxY": 673.0}, "class_id": 0, "box_caption": "Boerner 0.004", "scores": {"class_score": 0.0037212371826171875}, "domain": "pixel"}, {"position": {"minX": 294.0, "minY": 285.75, "maxX": 319.0, "maxY": 325.75}, "class_id": 6, "box_caption": "linnaeus 0.004", "scores": {"class_score": 0.003692626953125}, "domain": "pixel"}, {"position": {"minX": 379.75, "minY": 354.5, "maxX": 430.25, "maxY": 402.0}, "class_id": 4, "box_caption": "armandi 0.004", "scores": {"class_score": 0.00368499755859375}, "domain": "pixel"}, {"position": {"minX": 234.625, "minY": 446.0, "maxX": 274.25, "maxY": 477.5}, "class_id": 1, "box_caption": "Leconte 0.004", "scores": {"class_score": 0.0036792755126953125}, "domain": "pixel"}, {"position": {"minX": 378.75, "minY": 644.0, "maxX": 412.25, "maxY": 662.0}, "class_id": 5, "box_caption": "coleoptera 0.004", "scores": {"class_score": 0.0036792755126953125}, "domain": "pixel"}, {"position": {"minX": 161.25, "minY": 305.5, "maxX": 214.25, "maxY": 378.0}, "class_id": 0, "box_caption": "Boerner 0.004", "scores": {"class_score": 0.0036792755126953125}, "domain": "pixel"}, {"position": {"minX": 289.75, "minY": 289.5, "maxX": 313.75, "maxY": 322.5}, "class_id": 2, "box_caption": "Linnaeus 0.004", "scores": {"class_score": 0.0036716461181640625}, "domain": "pixel"}, {"position": {"minX": 248.0, "minY": 557.5, "maxX": 301.5, "maxY": 596.5}, "class_id": 1, "box_caption": "Leconte 0.004", "scores": {"class_score": 0.0036640167236328125}, "domain": "pixel"}, {"position": {"minX": 599.5, "minY": 83.875, "maxX": 599.5, "maxY": 185.125}, "class_id": 5, "box_caption": "coleoptera 0.004", "scores": {"class_score": 0.0036640167236328125}, "domain": "pixel"}, {"position": {"minX": 171.375, "minY": 299.0, "maxX": 209.625, "maxY": 347.0}, "class_id": 2, "box_caption": "Linnaeus 0.004", "scores": {"class_score": 0.0036563873291015625}, "domain": "pixel"}, {"position": {"minX": 136.25, "minY": 293.5, "maxX": 187.0, "maxY": 332.5}, "class_id": 4, "box_caption": "armandi 0.004", "scores": {"class_score": 0.0036487579345703125}, "domain": "pixel"}, {"position": {"minX": 171.375, "minY": 299.0, "maxX": 209.625, "maxY": 347.0}, "class_id": 4, "box_caption": "armandi 0.004", "scores": {"class_score": 0.003604888916015625}, "domain": "pixel"}, {"position": {"minX": 401.0, "minY": 338.5, "maxX": 435.0, "maxY": 395.5}, "class_id": 1, "box_caption": "Leconte 0.004", "scores": {"class_score": 0.003604888916015625}, "domain": "pixel"}, {"position": {"minX": 295.5, "minY": 306.5, "maxX": 316.0, "maxY": 330.0}, "class_id": 3, "box_caption": "acuminatus 0.004", "scores": {"class_score": 0.0036029815673828125}, "domain": "pixel"}, {"position": {"minX": 568.5, "minY": 54.75, "maxX": 601.5, "maxY": 167.625}, "class_id": 1, "box_caption": "Leconte 0.004", "scores": {"class_score": 0.0035953521728515625}, "domain": "pixel"}, {"position": {"minX": 236.75, "minY": 351.0, "maxX": 264.75, "maxY": 387.5}, "class_id": 0, "box_caption": "Boerner 0.004", "scores": {"class_score": 0.003589630126953125}, "domain": "pixel"}, {"position": {"minX": 362.75, "minY": 351.25, "maxX": 406.75, "maxY": 393.75}, "class_id": 0, "box_caption": "Boerner 0.004", "scores": {"class_score": 0.0035800933837890625}, "domain": "pixel"}, {"position": {"minX": 239.5, "minY": 441.25, "maxX": 276.5, "maxY": 469.75}, "class_id": 3, "box_caption": "acuminatus 0.004", "scores": {"class_score": 0.003574371337890625}, "domain": "pixel"}, {"position": {"minX": 164.625, "minY": 275.75, "maxX": 212.375, "maxY": 337.25}, "class_id": 5, "box_caption": "coleoptera 0.004", "scores": {"class_score": 0.0035552978515625}, "domain": "pixel"}, {"position": {"minX": 231.625, "minY": 352.0, "maxX": 275.5, "maxY": 403.5}, "class_id": 0, "box_caption": "Boerner 0.004", "scores": {"class_score": 0.003536224365234375}, "domain": "pixel"}, {"position": {"minX": 509.25, "minY": 91.6875, "maxX": 610.0, "maxY": 148.5}, "class_id": 2, "box_caption": "Linnaeus 0.004", "scores": {"class_score": 0.00353240966796875}, "domain": "pixel"}, {"position": {"minX": 509.25, "minY": 91.6875, "maxX": 610.0, "maxY": 148.5}, "class_id": 1, "box_caption": "Leconte 0.004", "scores": {"class_score": 0.0035266876220703125}, "domain": "pixel"}, {"position": {"minX": 388.5, "minY": 334.5, "maxX": 427.5, "maxY": 381.5}, "class_id": 5, "box_caption": "coleoptera 0.004", "scores": {"class_score": 0.003509521484375}, "domain": "pixel"}, {"position": {"minX": 532.5, "minY": 53.15625, "maxX": 539.5, "maxY": 141.25}, "class_id": 1, "box_caption": "Leconte 0.004", "scores": {"class_score": 0.0035037994384765625}, "domain": "pixel"}, {"position": {"minX": 296.75, "minY": 291.5, "maxX": 337.25, "maxY": 328.0}, "class_id": 5, "box_caption": "coleoptera 0.003", "scores": {"class_score": 0.0034961700439453125}, "domain": "pixel"}, {"position": {"minX": 145.5, "minY": 298.5, "maxX": 195.0, "maxY": 350.0}, "class_id": 2, "box_caption": "Linnaeus 0.003", "scores": {"class_score": 0.0034961700439453125}, "domain": "pixel"}, {"position": {"minX": 293.75, "minY": 307.5, "maxX": 312.25, "maxY": 329.5}, "class_id": 1, "box_caption": "Leconte 0.003", "scores": {"class_score": 0.00347900390625}, "domain": "pixel"}, {"position": {"minX": 489.25, "minY": 47.5, "maxX": 638.5, "maxY": 232.75}, "class_id": 1, "box_caption": "Leconte 0.003", "scores": {"class_score": 0.0034503936767578125}, "domain": "pixel"}, {"position": {"minX": 553.0, "minY": 75.5, "maxX": 636.0, "maxY": 195.0}, "class_id": 0, "box_caption": "Boerner 0.003", "scores": {"class_score": 0.003437042236328125}, "domain": "pixel"}, {"position": {"minX": 266.5, "minY": 562.0, "maxX": 314.5, "maxY": 640.0}, "class_id": 0, "box_caption": "Boerner 0.003", "scores": {"class_score": 0.0034332275390625}, "domain": "pixel"}, {"position": {"minX": 327.5, "minY": 433.5, "maxX": 370.5, "maxY": 480.0}, "class_id": 6, "box_caption": "linnaeus 0.003", "scores": {"class_score": 0.0034275054931640625}, "domain": "pixel"}, {"position": {"minX": 378.75, "minY": 644.0, "maxX": 412.25, "maxY": 662.0}, "class_id": 4, "box_caption": "armandi 0.003", "scores": {"class_score": 0.0034236907958984375}, "domain": "pixel"}, {"position": {"minX": 405.75, "minY": 326.5, "maxX": 445.75, "maxY": 379.0}, "class_id": 1, "box_caption": "Leconte 0.003", "scores": {"class_score": 0.0034084320068359375}, "domain": "pixel"}, {"position": {"minX": 609.0, "minY": 80.75, "maxX": 615.0, "maxY": 167.75}, "class_id": 6, "box_caption": "linnaeus 0.003", "scores": {"class_score": 0.0034027099609375}, "domain": "pixel"}, {"position": {"minX": 577.0, "minY": 107.875, "maxX": 628.0, "maxY": 219.375}, "class_id": 1, "box_caption": "Leconte 0.003", "scores": {"class_score": 0.0033969879150390625}, "domain": "pixel"}, {"position": {"minX": 294.0, "minY": 285.75, "maxX": 319.0, "maxY": 325.75}, "class_id": 2, "box_caption": "Linnaeus 0.003", "scores": {"class_score": 0.0033779144287109375}, "domain": "pixel"}, {"position": {"minX": 118.75, "minY": 545.0, "maxX": 132.125, "maxY": 629.0}, "class_id": 0, "box_caption": "Boerner 0.003", "scores": {"class_score": 0.0033664703369140625}, "domain": "pixel"}, {"position": {"minX": 295.25, "minY": 438.75, "maxX": 336.75, "maxY": 478.75}, "class_id": 1, "box_caption": "Leconte 0.003", "scores": {"class_score": 0.003360748291015625}, "domain": "pixel"}, {"position": {"minX": 158.125, "minY": 288.5, "maxX": 191.375, "maxY": 331.0}, "class_id": 1, "box_caption": "Leconte 0.003", "scores": {"class_score": 0.0033092498779296875}, "domain": "pixel"}, {"position": {"minX": 347.5, "minY": 642.0, "maxX": 396.0, "maxY": 673.0}, "class_id": 4, "box_caption": "armandi 0.003", "scores": {"class_score": 0.003307342529296875}, "domain": "pixel"}], "class_labels": {"0": "Boerner", "1": "Leconte", "2": "Linnaeus", "3": "acuminatus", "4": "armandi", "5": "coleoptera", "6": "linnaeus"}}